widecity_bill_generator/__init__.py
widecity_bill_generator/gst.py
widecity_billy-0.0.8.dist-info/LICENSE
widecity_billy-0.0.8.dist-info/METADATA
widecity_billy-0.0.8.dist-info/WHEEL
widecity_billy-0.0.8.dist-info/top_level.txt
widecity_billy-0.0.8.dist-info/RECORD
